{"amenities":["creber","carpo sordeo","addo rerum","vacuus villa","eos verto","tamen adimpleo","cohibeo conatus","toties","vitae","animi","impedit"],"category":"AI","subcategory":"smart contracts","city":"West Buddystead","description":"Truculenter ante ter creo sum. Aperiam arbor vallum ubi tamisium utroque ver aegre. Studio demens abbas vindico tabula.","id":"445007b3-6ba1-41e9-aabf-5995b09b6c36","logo":"https://picsum.photos/seed/oBBQ2AUtH/370/539","name":"Friesen Inc","openingHours":[{"opens":"T09:00:00Z","closes":"T09:00:00Z","dayOfWeek":"MONDAY"},{"opens":"T09:00:00Z","closes":"T09:00:00Z","dayOfWeek":"TUESDAY"},{"opens":"T09:00:00Z","closes":"T09:00:00Z","dayOfWeek":"WEDNESDAY"},{"opens":"T09:00:00Z","closes":"T09:00:00Z","dayOfWeek":"THURSDAY"},{"opens":"T09:00:00Z","closes":"T09:00:00Z","dayOfWeek":"FRIDAY"},{"opens":"T09:00:00Z","closes":"T09:00:00Z","dayOfWeek":"SATURDAY"},{"opens":"T09:00:00Z","closes":"T09:00:00Z","dayOfWeek":"SUNDAY"}],"paymentOptions":["TRANSFER"],"rating":3,"street":"Maxwell Underpass","telephone":"384-546-1969 x9128","tags":["usitas","armarium","conservo","ager","vespillo"],"town":"Franklin County","reviews":[{"id":"292d67f1-9015-4e6a-bd15-d05cf979c61a","createdOn":"Sun May 11 2025 16:01:07 GMT+0100 (West Africa Standard Time)","reviewBody":"Curtus adipiscor reprehenderit cursim cuppedia. Rerum ullus earum deputo. Consectetur vehemens brevis.","reviewRating":1.7,"reviewer":{"name":"Ada Maggio","email":"Anita_Swift@hotmail.com","telephone":"1-991-730-1604 x0333"}},{"id":"1df36419-cb82-4751-8ccc-90d892c09bb4","createdOn":"Tue Nov 12 2024 00:54:16 GMT+0100 (West Africa Standard Time)","reviewBody":"Ascisco tendo quisquam. Adeo aut utique quos arguo suscipit. Cito degero ultra arbor arcesso.","reviewRating":2.5,"reviewer":{"name":"Janet Roob","email":"Gilbert17@gmail.com","telephone":"(513) 421-4321 x64308"}},{"id":"a92df5f5-1c3b-4367-b7b4-36319a376ae6","createdOn":"Tue Mar 18 2025 14:10:25 GMT+0100 (West Africa Standard Time)","reviewBody":"Defluo volup depereo eaque victus. Vulnero pel admoveo comis occaecati callide sodalitas tenuis. Atque cibo consectetur stillicidium arca acerbitas vesper asporto decet alo.","reviewRating":2,"reviewer":{"name":"Juan Marquardt","email":"Virgie52@gmail.com","telephone":"(327) 214-6053 x97305"}},{"id":"55c99a3e-f0ad-4632-885f-aa3ce6d20501","createdOn":"Mon Oct 07 2024 14:39:45 GMT+0100 (West Africa Standard Time)","reviewBody":"Crapula color demo. Termes thymum cubicularis auditor alo tandem sursum tempora testimonium. Calco undique curatio tum.","reviewRating":1.9,"reviewer":{"name":"Lorene Ullrich-Flatley","email":"Jazmyn_Hartmann-Rempel88@hotmail.com","telephone":"328.646.7568"}},{"id":"3d5a592a-eba6-4f1d-bfbf-7914d9cd7b48","createdOn":"Thu Oct 10 2024 07:47:22 GMT+0100 (West Africa Standard Time)","reviewBody":"Teres spero venustas. Copia terminatio angulus qui validus debeo qui campana. Pecus tui theologus arbustum.","reviewRating":3.2,"reviewer":{"name":"Carolyn Shanahan Sr.","email":"Felicity_Franecki@gmail.com","telephone":"1-653-352-9206"}},{"id":"efc69330-bb36-429b-825f-1181b52ff2ff","createdOn":"Sun Jun 15 2025 22:00:03 GMT+0100 (West Africa Standard Time)","reviewBody":"Cervus annus curso admiratio compello. Praesentium tabesco stips. Spes casso excepturi abbas.","reviewRating":1.4,"reviewer":{"name":"Roosevelt Kuhn","email":"Ramona.Hayes76@gmail.com","telephone":"1-535-487-9144 x21253"}}],"services":[{"id":"dd28daab-a61c-4da3-9720-d3b1f7745c08","name":"Ergonomic Gold Bike","description":"Introducing the Vanuatu-inspired Pants, blending possible style with local craftsmanship","priceSpecification":{"price":35000,"priceCurrency":"₦"}},{"id":"57ce14b0-381a-40ab-923f-2ad3982ca184","name":"Bespoke Cotton Fish","description":"Experience the silver brilliance of our Car, perfect for probable environments","priceSpecification":{"price":26000,"priceCurrency":"₦"}},{"id":"337a11f2-3b73-4ece-b203-c59277fe50b5","name":"Fresh Silk Shoes","description":"Featuring Seaborgium-enhanced technology, our Shoes offers unparalleled oval performance","priceSpecification":{"price":10000,"priceCurrency":"₦"}},{"id":"6dcae075-b40a-4c6f-9842-465e9fb11ca1","name":"Fantastic Marble Shoes","description":"The plum Cheese combines Trinidad and Tobago aesthetics with Tantalum-based durability","priceSpecification":{"price":27000,"priceCurrency":"₦"}},{"id":"db2802f1-0e3a-4a35-8ec1-26e1f30adcf5","name":"Generic Metal Pants","description":"Our tender-inspired Soap brings a taste of luxury to your rotating lifestyle","priceSpecification":{"price":30000,"priceCurrency":"₦"}},{"id":"4191925b-3b39-4b18-aba6-c4ad7c98f5c7","name":"Refined Cotton Sausages","description":"The maroon Towels combines Greece aesthetics with Holmium-based durability","priceSpecification":{"price":40000,"priceCurrency":"₦"}},{"id":"b1160c94-bdb5-4385-b81b-931aa1691cc6","name":"Unbranded Granite Cheese","description":"Discover the cuddly new Chair with an exciting mix of Metal ingredients","priceSpecification":{"price":47000,"priceCurrency":"₦"}},{"id":"52afe30e-6759-4d56-bce5-43866f99d90b","name":"Elegant Concrete Pants","description":"The sleek and numb Keyboard comes with lime LED lighting for smart functionality","priceSpecification":{"price":31000,"priceCurrency":"₦"}},{"id":"b7967b4f-666d-41e8-aed8-2b0b639506cc","name":"Electronic Ceramic Keyboard","description":"Our crunchy-inspired Chicken brings a taste of luxury to your heavenly lifestyle","priceSpecification":{"price":27000,"priceCurrency":"₦"}},{"id":"a4fdc1bf-25c7-40d6-8356-43ea742d1f62","name":"Refined Cotton Salad","description":"Innovative Salad featuring murky technology and Metal construction","priceSpecification":{"price":46000,"priceCurrency":"₦"}},{"id":"071f7b35-3d1a-4299-b4c9-135a54881842","name":"Incredible Aluminum Chair","description":"The Robust zero defect local area network Fish offers reliable performance and fluffy design","priceSpecification":{"price":45000,"priceCurrency":"₦"}},{"id":"c151ea87-8647-4823-a7c6-56f6852de5dd","name":"Frozen Wooden Chips","description":"The sleek and subtle Ball comes with mint green LED lighting for smart functionality","priceSpecification":{"price":37000,"priceCurrency":"₦"}},{"id":"0b368825-64cf-44ab-99c5-ce0f8a8f8d4e","name":"Small Silk Tuna","description":"Ergonomic Keyboard made with Rubber for all-day serene support","priceSpecification":{"price":19000,"priceCurrency":"₦"}},{"id":"ec67d1ae-0caa-4dcc-8981-704bc6962ffe","name":"Refined Wooden Cheese","description":"Electronic Fish designed with Ceramic for uncommon performance","priceSpecification":{"price":32000,"priceCurrency":"₦"}},{"id":"693e5b64-d9a1-442a-b5ac-679a19ebc8da","name":"Generic Ceramic Bacon","description":"Innovative Shirt featuring unwilling technology and Cotton construction","priceSpecification":{"price":32000,"priceCurrency":"₦"}}]}