{"amenities":["patruus","approbo","capillus alii","animi","sublime decens","coaegresco utilis","eos verto","impedit","carpo sordeo","tamen adimpleo","illum","comminor","absum","vitae","creber","at"],"category":"experiences","subcategory":"metrics","city":"Shaynaboro","description":"Aperiam antepono arcesso. Socius defero cimentarius. Depopulo architecto cupiditate derideo tondeo.","id":"e829e00f-ab8b-453d-8bcc-5d9be2af715c","logo":"https://picsum.photos/seed/htjGTA2AYB/456/433","name":"Stamm Inc","openingHours":[{"opens":"T09:00:00Z","closes":"T09:00:00Z","dayOfWeek":"MONDAY"},{"opens":"T09:00:00Z","closes":"T09:00:00Z","dayOfWeek":"TUESDAY"},{"opens":"T09:00:00Z","closes":"T09:00:00Z","dayOfWeek":"WEDNESDAY"},{"opens":"T09:00:00Z","closes":"T09:00:00Z","dayOfWeek":"THURSDAY"},{"opens":"T09:00:00Z","closes":"T09:00:00Z","dayOfWeek":"FRIDAY"},{"opens":"T09:00:00Z","closes":"T09:00:00Z","dayOfWeek":"SATURDAY"},{"opens":"T09:00:00Z","closes":"T09:00:00Z","dayOfWeek":"SUNDAY"}],"paymentOptions":["TRANSFER"],"rating":3.8,"street":"Braun Pines","telephone":"(523) 451-2383 x1781","tags":["dolorum","ager","harum","deporto"],"town":"Avon","reviews":[{"id":"4e95138a-334a-416b-bad3-876f9598de23","createdOn":"Sun Aug 10 2025 23:42:07 GMT+0100 (West Africa Standard Time)","reviewBody":"Termes tero volo neque correptius. Adipisci curtus demitto color verbum. Traho dignissimos omnis.","reviewRating":3,"reviewer":{"name":"Gwen Heller","email":"Dakota36@gmail.com","telephone":"1-344-952-5936"}},{"id":"4aea1542-9aec-4d96-b334-a4bc359a1575","createdOn":"Sat May 10 2025 02:37:09 GMT+0100 (West Africa Standard Time)","reviewBody":"Antea possimus condico claro cena utroque vestrum crebro soluta. Patruus conculco beatus. Coniuratio esse patior libero torrens theca clam cruciamentum nihil.","reviewRating":2,"reviewer":{"name":"Mabel Hauck","email":"Johnnie84@yahoo.com","telephone":"993.634.1523 x0015"}},{"id":"5d5556a1-91e5-4e53-8eff-90bcc2fe2848","createdOn":"Tue Apr 08 2025 14:28:58 GMT+0100 (West Africa Standard Time)","reviewBody":"Cetera tunc vester cenaculum. Vespillo teres congregatio. Adaugeo conicio causa ea contra quas alter votum.","reviewRating":4.3,"reviewer":{"name":"Bessie Cronin","email":"Eliane_Sanford@gmail.com","telephone":"219.859.1668 x2141"}},{"id":"718e8e90-e907-4794-ba0c-f6c1a03e09ec","createdOn":"Mon Jun 23 2025 13:28:39 GMT+0100 (West Africa Standard Time)","reviewBody":"Paens traho natus usque sodalitas agnosco. Tremo umbra veniam virtus spero. Clementia ars voluptatibus velit adiuvo vinculum.","reviewRating":3.7,"reviewer":{"name":"Mr. Freddie Moore","email":"Summer.Dickinson@yahoo.com","telephone":"674.459.1128"}}],"services":[{"id":"27dfbec8-8d34-4e6c-a076-c52ff2b10d91","name":"Modern Silk Table","description":"Introducing the Macao-inspired Sausages, blending broken style with local craftsmanship","priceSpecification":{"price":21000,"priceCurrency":"₦"}},{"id":"94373e3f-b150-4441-89d8-e12b0c71c449","name":"Gorgeous Bamboo Gloves","description":"The tan Bacon combines Greenland aesthetics with Thulium-based durability","priceSpecification":{"price":10000,"priceCurrency":"₦"}},{"id":"c384608e-6f5a-4df7-8884-0eef86d4335e","name":"Luxurious Steel Gloves","description":"Our savory-inspired Bike brings a taste of luxury to your grubby lifestyle","priceSpecification":{"price":7000,"priceCurrency":"₦"}},{"id":"6e030de4-42aa-4269-b98f-3210d4e3d80f","name":"Frozen Ceramic Chair","description":"New turquoise Pizza with ergonomic design for total comfort","priceSpecification":{"price":6000,"priceCurrency":"₦"}},{"id":"677ceac8-c156-4247-9ce0-e4af91d8a003","name":"Oriental Silk Salad","description":"The Quinn Tuna is the latest in a series of ordinary products from Rosenbaum Inc","priceSpecification":{"price":32000,"priceCurrency":"₦"}},{"id":"c518040a-e300-4499-9ecb-e1ad991d70e2","name":"Frozen Bronze Gloves","description":"Discover the dolphin-like agility of our Ball, perfect for zesty users","priceSpecification":{"price":50000,"priceCurrency":"₦"}},{"id":"ea236240-6de1-4b87-b648-ac3d07a102f7","name":"Unbranded Gold Tuna","description":"Innovative Soap featuring limping technology and Steel construction","priceSpecification":{"price":17000,"priceCurrency":"₦"}},{"id":"418e24a8-a579-49eb-943b-db6e3dddc5b7","name":"Modern Wooden Computer","description":"The sleek and sturdy Gloves comes with indigo LED lighting for smart functionality","priceSpecification":{"price":27000,"priceCurrency":"₦"}},{"id":"b515455f-8431-44f1-86f2-c62f4ba4b614","name":"Handmade Concrete Chair","description":"New Towels model with 81 GB RAM, 221 GB storage, and busy features","priceSpecification":{"price":31000,"priceCurrency":"₦"}}]}